flask_spring/__init__.py
flask_spring-0.1.0.dist-info/DESCRIPTION.rst
flask_spring-0.1.0.dist-info/METADATA
flask_spring-0.1.0.dist-info/RECORD
flask_spring-0.1.0.dist-info/WHEEL
flask_spring-0.1.0.dist-info/metadata.json
flask_spring-0.1.0.dist-info/top_level.txt
