Metadata-Version: 2.0
Name: flask-spring
Version: 0.1.0
Summary: Adds the Spring framework support to your Flask application
Home-page: https://github.com/oggthemiffed/Flask-Spring
Author: David Anderson
Author-email: herbaliser1978@gmail.com
License: MIT
Platform: UNKNOWN
Classifier: Environment :: Web Environment
Classifier: Intended Audience :: Developers
Classifier: License :: OSI Approved :: MIT License
Classifier: Topic :: Internet :: WWW/HTTP :: Dynamic Content
Classifier: Topic :: Software Development :: Libraries :: Python Modules
Classifier: Programming Language :: Python
Classifier: Programming Language :: Python :: 2
Classifier: Programming Language :: Python :: 2.7
Requires-Dist: flask
Requires-Dist: pyyaml
Requires-Dist: springpython
